PYMOD/PYMOD.py
PYMOD/__init__.py
pymod_outliers-1.0.0.dist-info/licenses/LICENSE
pymod_outliers-1.0.0.dist-info/METADATA
pymod_outliers-1.0.0.dist-info/WHEEL
pymod_outliers-1.0.0.dist-info/top_level.txt
pymod_outliers-1.0.0.dist-info/RECORD
