Metadata-Version: 2.4
Name: pymod-outliers
Version: 1.0.0
Summary: Multivariate Outlier Detection for Solar Photovoltaic Systems
Author-email: SAAD BASMA <b.saad@uiz.ac.ma>, BOUADA MOHAMED <mohamed.bouada.38@edu.uiz.ac.ma>
Maintainer-email: SAAD BASMA <b.saad@uiz.ac.ma>
License: MIT
Keywords: outlier detection,solar energy,photovoltaic,PV systems,anomaly detection,DBSCAN,data cleaning,time series
Classifier: Development Status :: 4 - Beta
Classifier: Intended Audience :: Science/Research
Classifier: Intended Audience :: Developers
Classifier: License :: OSI Approved :: MIT License
Classifier: Programming Language :: Python :: 3
Classifier: Programming Language :: Python :: 3.7
Classifier: Programming Language :: Python :: 3.8
Classifier: Programming Language :: Python :: 3.9
Classifier: Programming Language :: Python :: 3.10
Classifier: Programming Language :: Python :: 3.11
Classifier: Programming Language :: Python :: 3.12
Classifier: Topic :: Scientific/Engineering
Classifier: Topic :: Scientific/Engineering :: Artificial Intelligence
Classifier: Topic :: Software Development :: Libraries :: Python Modules
Classifier: Operating System :: OS Independent
Requires-Python: >=3.7
Requires-Dist: numpy>=1.19.0
Requires-Dist: pandas>=1.1.0
Requires-Dist: scipy>=1.5.0
Requires-Dist: scikit-learn>=0.23.0
Requires-Dist: matplotlib>=3.3.0
